Workbook

Sheet Read me
A1: Routledge Direct: FY2026 budget planner
A2: Paid media for 1 October 2025 to 30 September 2026, built on gross profit. Simulated data.
A4: What it does | B4: Shows what a paid media budget is expected to bring in FY2026: new customers, net revenue and gross profit, under last click and under position based attribution side by side, and what each channel is worth if only part of its credited customers are genuinely new.
A5: How to use it | B5: Edit the yellow cells with blue text only. On the Planner, change a channel's FY2026 budget in column C, or an assumption in B5 to B9. Every other figure, on every sheet, follows.
A6: Sheets | B6: Planner: budgets, assumptions and results. Recommendation: the proposed split, what it changes and how sure we are. Scenarios: each channel at 30, 50 and 80 percent genuinely new. Data: the verified figures behind it all, with their sources.
A7: Colours | B7: Yellow with blue text: an input to change. Grey: a verified figure from BigQuery, not to be edited. White: a formula. Red: a flag or a loss.
A8: Definitions | B8: Net revenue is after discounts and refunds. Gross profit is net revenue less product, shipping, payment and affiliate costs, before ad spend. Last click credits an order to the channel recorded on it at checkout. Position based gives 40 percent to the first session in the 30 days before the order, 40 to the last and 20 across the middle. ROAS is net revenue over ad spend.
A9: Starting point | B9: FY2025, 1 October 2024 to 30 September 2025: $498,948 of ad spend on the five paid channels that carry campaigns. The Planner opens on the recommended FY2026 split.
A10: Rules built in | B10: No added budget for Meta Prospecting while its checkout drop off is unexplained (flagged in red). Meta Prospecting's cost per click rises 8 percent a year. Budgets moved more than 25 percent from FY2025 are flagged, because the data cannot show returns that far out.
A11: What it does not do | B11: It does not measure incrementality: no holdout or experiment exists in the data, so the share of genuinely new customers is an assumption tested at several levels. It does not plan email, organic search, direct or referral, which carry no ad spend. Google Paid Untagged and Meta Untagged have no spend of their own and are left out.

Sheet Planner
A1: FY2026 paid media planner
A2: Change a budget in column C (yellow) or an assumption in B5 to B9 and every figure moves. Grey and white cells are calculated.
A4: Assumptions
A5: Share of credited new customers who are genuinely new (incrementality) | B5: 0.5 | C5: Not measurable from this data: no holdout or experiment exists. 50 percent is a middle case; the Scenarios sheet shows 30, 50 and 80 percent.
A6: Meta Prospecting cost per click growth, a year | B6: 0.08 | C6: Measured at about 8 percent a year (Data, B34).
A7: Meta Prospecting click to order growth, a year | B7: 0 | C7: Measured at about 9 percent a year (Data, B35), which has kept its cost per order flat. Set to 0 on purpose: if that gain stalls, cost per order follows cost per click up.
A8: Largest budget change the data supports | B8: 0.25 | C8: Returns are scaled in proportion to spend, which only holds near the budgets actually run, so the return on a much larger or smaller budget cannot be read from the data. Changes beyond this are flagged.
A9: Adopt the commission changes Pay on credit and Refund hold (1 yes, 0 no) | B9: 1 | C9: Pay on credit: pay coupon partners only on orders credited to them. Refund hold: hold commission 45 days and drop it if the order is refunded in that time.
A12: Channel | B12: FY2025 ad spend | C12: FY2026 budget | D12: Change on FY2025 | E12: Return per dollar against FY2025 | F12: New customers credited | G12: Net revenue, last click | H12: Gross profit, last click | I12: Gross profit after ad spend, last click | J12: Gross profit, position based | K12: Gross profit after ad spend, position based | L12: ROAS, last click | M12: ROAS, position based | N12: 12 month gross profit from genuinely new customers | O12: The same, after ad spend | P12: Break even share of genuinely new customers | Q12: Clears the assumed share? | R12: Flags
A13: Google Brand | B13: =Data!B5 | C13: 31289.45 | D13: =IF(B13=0,"",C13/B13-1) | E13: =IF(A13="Meta Prospecting",(1+$B$7)/(1+$B$6),1) | F13: =C13*E13/Data!H5 | G13: =C13*E13*Data!C5/Data!B5 | H13: =C13*E13*Data!D5/Data!B5 | I13: =H13-C13 | J13: =H13*Data!F5/Data!E5 | K13: =J13-C13 | L13: =IF(C13=0,"",G13/C13) | M13: =IF(C13=0,"",E13*Data!G5) | N13: =F13*$B$5*Data!J5 | O13: =N13-C13 | P13: =Data!H5/E13/Data!J5 | Q13: =IF($B$5>=P13,"Yes","No") | R13: =IF(AND(A13="Meta Prospecting",C13>B13),"No added budget while the checkout drop off is unexplained. ","")&IF(ABS(C13/B13-1)>$B$8,"Beyond the range the data supports.","")
A14: Google Non Brand | B14: =Data!B6 | C14: 138089.08 | D14: =IF(B14=0,"",C14/B14-1) | E14: =IF(A14="Meta Prospecting",(1+$B$7)/(1+$B$6),1) | F14: =C14*E14/Data!H6 | G14: =C14*E14*Data!C6/Data!B6 | H14: =C14*E14*Data!D6/Data!B6 | I14: =H14-C14 | J14: =H14*Data!F6/Data!E6 | K14: =J14-C14 | L14: =IF(C14=0,"",G14/C14) | M14: =IF(C14=0,"",E14*Data!G6) | N14: =F14*$B$5*Data!J6 | O14: =N14-C14 | P14: =Data!H6/E14/Data!J6 | Q14: =IF($B$5>=P14,"Yes","No") | R14: =IF(AND(A14="Meta Prospecting",C14>B14),"No added budget while the checkout drop off is unexplained. ","")&IF(ABS(C14/B14-1)>$B$8,"Beyond the range the data supports.","")
A15: Google Shopping | B15: =Data!B7 | C15: 80300.48 | D15: =IF(B15=0,"",C15/B15-1) | E15: =IF(A15="Meta Prospecting",(1+$B$7)/(1+$B$6),1) | F15: =C15*E15/Data!H7 | G15: =C15*E15*Data!C7/Data!B7 | H15: =C15*E15*Data!D7/Data!B7 | I15: =H15-C15 | J15: =H15*Data!F7/Data!E7 | K15: =J15-C15 | L15: =IF(C15=0,"",G15/C15) | M15: =IF(C15=0,"",E15*Data!G7) | N15: =F15*$B$5*Data!J7 | O15: =N15-C15 | P15: =Data!H7/E15/Data!J7 | Q15: =IF($B$5>=P15,"Yes","No") | R15: =IF(AND(A15="Meta Prospecting",C15>B15),"No added budget while the checkout drop off is unexplained. ","")&IF(ABS(C15/B15-1)>$B$8,"Beyond the range the data supports.","")
A16: Meta Prospecting | B16: =Data!B8 | C16: 205487.28 | D16: =IF(B16=0,"",C16/B16-1) | E16: =IF(A16="Meta Prospecting",(1+$B$7)/(1+$B$6),1) | F16: =C16*E16/Data!H8 | G16: =C16*E16*Data!C8/Data!B8 | H16: =C16*E16*Data!D8/Data!B8 | I16: =H16-C16 | J16: =H16*Data!F8/Data!E8 | K16: =J16-C16 | L16: =IF(C16=0,"",G16/C16) | M16: =IF(C16=0,"",E16*Data!G8) | N16: =F16*$B$5*Data!J8 | O16: =N16-C16 | P16: =Data!H8/E16/Data!J8 | Q16: =IF($B$5>=P16,"Yes","No") | R16: =IF(AND(A16="Meta Prospecting",C16>B16),"No added budget while the checkout drop off is unexplained. ","")&IF(ABS(C16/B16-1)>$B$8,"Beyond the range the data supports.","")
A17: Meta Retargeting | B17: =Data!B9 | C17: 43781.62 | D17: =IF(B17=0,"",C17/B17-1) | E17: =IF(A17="Meta Prospecting",(1+$B$7)/(1+$B$6),1) | F17: =C17*E17/Data!H9 | G17: =C17*E17*Data!C9/Data!B9 | H17: =C17*E17*Data!D9/Data!B9 | I17: =H17-C17 | J17: =H17*Data!F9/Data!E9 | K17: =J17-C17 | L17: =IF(C17=0,"",G17/C17) | M17: =IF(C17=0,"",E17*Data!G9) | N17: =F17*$B$5*Data!J9 | O17: =N17-C17 | P17: =Data!H9/E17/Data!J9 | Q17: =IF($B$5>=P17,"Yes","No") | R17: =IF(AND(A17="Meta Prospecting",C17>B17),"No added budget while the checkout drop off is unexplained. ","")&IF(ABS(C17/B17-1)>$B$8,"Beyond the range the data supports.","")
A18: Total | B18: =SUM(B13:B17) | C18: =SUM(C13:C17) | D18: =C18/B18-1 | F18: =SUM(F13:F17) | G18: =SUM(G13:G17) | H18: =SUM(H13:H17) | I18: =SUM(I13:I17) | J18: =SUM(J13:J17) | K18: =SUM(K13:K17) | L18: =G18/C18 | N18: =SUM(N13:N17) | O18: =SUM(O13:O17)
A20: FY2026 against FY2025
A21: Measure | B21: FY2025 | C21: FY2026 plan | D21: Change
A22: Ad spend | B22: =SUM(Data!B5:B9) | C22: =C18 | D22: =C22-B22
A23: New customers credited, at three year cost per new customer | B23: =SUMPRODUCT(Data!B5:B9/Data!H5:H9) | C23: =F18 | D23: =C23-B23
A24: Net revenue, last click | B24: =SUM(Data!C5:C9) | C24: =G18 | D24: =C24-B24
A25: Gross profit, last click | B25: =SUM(Data!D5:D9) | C25: =H18 | D25: =C25-B25
A26: Gross profit after ad spend, last click | B26: =B25-B22 | C26: =I18 | D26: =C26-B26
A27: Gross profit after ad spend, position based | B27: =SUMPRODUCT(Data!D5:D9*Data!F5:F9/Data!E5:E9)-SUM(Data!B5:B9) | C27: =K18 | D27: =C27-B27
A28: 12 month gross profit from genuinely new customers, after ad spend | B28: =SUMPRODUCT(Data!B5:B9/Data!H5:H9*Data!J5:J9)*B5-SUM(Data!B5:B9) | C28: =O18 | D28: =C28-B28
A29: Affiliate commission saved by Pay on credit and Refund hold, a year | B29: 0 | C29: =B9*Data!B23/Data!B24 | D29: =C29-B29
A30: Gross profit after ad spend and commission saved, last click | B30: =B26+B29 | C30: =C26+C29 | D30: =C30-B30
A31: Gross profit after ad spend and commission saved, position based | B31: =B27+B29 | C31: =C27+C29 | D31: =C31-B31
A33: FY2025 is the year as it happened: Meta Prospecting at this year's cost, new customers at the three year cost per new customer. The 12 month line uses the same assumed share for both years.

Sheet Recommendation
A1: Recommended FY2026 split
A2: Total paid media held at FY2025 level and moved on gross profit, with the Pay on credit and Refund hold commission changes. Uses the assumptions on the Planner.
A4: Channel | B4: FY2025 ad spend | C4: Recommended change | D4: Recommended FY2026 budget | E4: Budget moved | F4: Change in gross profit after ad spend, last click | G4: Change in gross profit after ad spend, position based | H4: Change in 12 month gross profit from genuinely new customers, after ad spend | I4: Confidence | J4: Why
A5: Google Brand | B5: =Data!B5 | C5: 0 | D5: =B5*(1+C5) | E5: =D5-B5 | F5: =E5*(Planner!E13*Data!D5/Data!B5-1) | G5: =E5*(Planner!E13*Data!D5/Data!B5*Data!F5/Data!E5-1) | H5: =E5*(Planner!E13/Data!H5*Planner!$B$5*Data!J5-1) | I5: Medium | J5: Hold, and test. Highest return under last click, linear and position based (under first click it ranks third, 3.61 against Google Non Brand 8.01 and Meta Prospecting 5.33) and breaks even if only 11.0 percent of its new customers are genuinely new, but 84.0 percent of the orders it closes began on another channel. Its spend is too small to matter until a holdout says how much of it is needed.
A6: Google Non Brand | B6: =Data!B6 | C6: =-(B5*C5+B7*C7+B8*C8+B9*C9)/B6 | D6: =B6*(1+C6) | E6: =D6-B6 | F6: =E6*(Planner!E14*Data!D6/Data!B6-1) | G6: =E6*(Planner!E14*Data!D6/Data!B6*Data!F6/Data!E6-1) | H6: =E6*(Planner!E14/Data!H6*Planner!$B$5*Data!J6-1) | I6: Medium | J6: Receives what retargeting releases. Gains credit under position based (gross profit per dollar 3.26 to 4.23), opened 58.4 percent of the journeys it closed, 26.6 percent of its customers buy again within a year, and it breaks even at 24.5 percent genuinely new.
A7: Google Shopping | B7: =Data!B7 | C7: 0 | D7: =B7*(1+C7) | E7: =D7-B7 | F7: =E7*(Planner!E15*Data!D7/Data!B7-1) | G7: =E7*(Planner!E15*Data!D7/Data!B7*Data!F7/Data!E7-1) | H7: =E7*(Planner!E15/Data!H7*Planner!$B$5*Data!J7-1) | I7: Medium | J7: Hold. In the middle on break even (32.5 percent) and repeat (14.9 percent), fourth of five on gross profit per dollar under both rules, and it loses some credit under position based (2.71 to 2.10).
A8: Meta Prospecting | B8: =Data!B8 | C8: 0 | D8: =B8*(1+C8) | E8: =D8-B8 | F8: =E8*(Planner!E16*Data!D8/Data!B8-1) | G8: =E8*(Planner!E16*Data!D8/Data!B8*Data!F8/Data!E8-1) | H8: =E8*(Planner!E16/Data!H8*Planner!$B$5*Data!J8-1) | I8: High that no increase is warranted | J8: Hold, no added budget. Checkout to purchase is about 13 percent against 38 for Google traffic, cause unexplained; cost per click is rising about 8 percent a year; it needs 57.1 percent of its new customers to be genuinely new; 4.5 percent buy again. Position based says it opens journeys, so it is not cut either.
A9: Meta Retargeting | B9: =Data!B9 | C9: -0.2 | D9: =B9*(1+C9) | E9: =D9-B9 | F9: =E9*(Planner!E17*Data!D9/Data!B9-1) | G9: =E9*(Planner!E17*Data!D9/Data!B9*Data!F9/Data!E9-1) | H9: =E9*(Planner!E17/Data!H9*Planner!$B$5*Data!J9-1) | I9: Medium, last click disagrees | J9: Cut by a fifth. It opened only 12.2 percent of the journeys it closed, its gross profit per dollar halves under position based (3.88 to 2.00, the lowest), 6.9 percent buy again and it needs 39.9 percent genuinely new. Last click alone would keep it, so the cut is small and reversible.
A10: Affiliate commission: Pay on credit and Refund hold | F10: =Data!B23/Data!B24 | G10: =Data!B23/Data!B24 | H10: =Data!B23/Data!B24 | I10: High on the amount; the risk is coupon partners leaving | J10: Saved $132,607 over three years on the actual transactions, $44,202 a year. Coupon partners keep their commission on the orders they win unless the order is refunded; content partners lose only the $1,770.86 of commission on their refunded orders. If some partners leave, the orders at stake are mainly those credited to coupon partners, whose customers are the least valuable in the base (12 month gross profit $81.95, 2.5 percent repeat).
A11: Change on keeping FY2025 budgets | B11: =SUM(B5:B9) | C11: =D11/B11-1 | D11: =SUM(D5:D9) | E11: =SUM(E5:E9) | F11: =SUM(F5:F10) | G11: =SUM(G5:G10) | H11: =SUM(H5:H10) | J11: Each column is the change against spending FY2025's budgets again in FY2026, under the same assumptions, so it shows the effect of the decision and nothing else.
A13: First holdout test: pause brand search in the UK
A14: Weeks paused | B14: 8 | C14: Edit to suit. A longer pause gives a clearer read and costs more if brand search turns out to be needed.
A15: UK share of brand search spend | B15: =Data!B36 | C15: Assumed equal to the UK share of net revenue, 25.1 percent. Replace it with the UK brand campaign's actual share from Google Ads before the test.
A16: Brand search spend saved during the pause | B16: =Data!B5*B14/52*B15 | C16: FY2025 brand spend for the weeks paused.
A17: Gross profit brand search is credited with in those weeks, last click | B17: =Data!D5*B14/52*B15 | C17: What last click says is at risk.
A18: Share of that gross profit that has to disappear for brand search to be worth its cost | B18: =B16/B17 | C18: If UK gross profit, compared with the US and ROW over the same weeks and the same weeks last year, falls by less than this share of brand search's credited gross profit, UK brand search costs more than the gross profit it protects.
A20: Limits of this plan
A21: Incrementality is assumed, not measured. Nothing in the data shows how many of a channel's customers would have bought without it; the brand search holdout is the first step to finding out.
A22: Returns are scaled in proportion to spend, which only holds near the budgets actually run; the point where extra spend stops paying cannot be found from this data. Budget changes beyond the range set on the Planner are flagged.
A23: Last click and position based disagree about retargeting, so its cut is small, and nothing is moved on either rule alone.
A24: Gross profit is before ad spend unless a column says otherwise; email, organic search, direct and referral carry no ad spend and are not budgeted here.
A25: All figures are from simulated data. No figure describes actual Taylor & Francis performance.

Sheet Scenarios
A1: How much has to be genuinely new
A2: Twelve month gross profit from genuinely new customers, after ad spend, at the FY2026 budgets on the Planner. Change the shares in row 5.
A5: Assumed share of credited new customers who are genuinely new | F5: 0.3 | G5: 0.5 | H5: 0.8
A6: Channel | B6: FY2026 budget | C6: New customers credited | D6: 12 month gross profit per new customer | E6: Break even share, unit economics | F6: After ad spend at the first share | G6: After ad spend at the second share | H6: After ad spend at the third share | I6: Break even share at FY2026 cost
A7: Google Brand | B7: =Planner!C13 | C7: =Planner!F13 | D7: =Data!J5 | E7: =Data!I5/Data!J5 | F7: =C7*F$5*D7-B7 | G7: =C7*G$5*D7-B7 | H7: =C7*H$5*D7-B7 | I7: =Planner!P13
A8: Google Non Brand | B8: =Planner!C14 | C8: =Planner!F14 | D8: =Data!J6 | E8: =Data!I6/Data!J6 | F8: =C8*F$5*D8-B8 | G8: =C8*G$5*D8-B8 | H8: =C8*H$5*D8-B8 | I8: =Planner!P14
A9: Google Shopping | B9: =Planner!C15 | C9: =Planner!F15 | D9: =Data!J7 | E9: =Data!I7/Data!J7 | F9: =C9*F$5*D9-B9 | G9: =C9*G$5*D9-B9 | H9: =C9*H$5*D9-B9 | I9: =Planner!P15
A10: Meta Prospecting | B10: =Planner!C16 | C10: =Planner!F16 | D10: =Data!J8 | E10: =Data!I8/Data!J8 | F10: =C10*F$5*D10-B10 | G10: =C10*G$5*D10-B10 | H10: =C10*H$5*D10-B10 | I10: =Planner!P16
A11: Meta Retargeting | B11: =Planner!C17 | C11: =Planner!F17 | D11: =Data!J9 | E11: =Data!I9/Data!J9 | F11: =C11*F$5*D11-B11 | G11: =C11*G$5*D11-B11 | H11: =C11*H$5*D11-B11 | I11: =Planner!P17
A12: Total | B12: =SUM(B7:B11) | C12: =SUM(C7:C11) | F12: =SUM(F7:F11) | G12: =SUM(G7:G11) | H12: =SUM(H7:H11)
A13: Channels that more than pay for themselves | F13: =COUNTIF(F7:F11,">=0")&" of 5" | G13: =COUNTIF(G7:G11,">=0")&" of 5" | H13: =COUNTIF(H7:H11,">=0")&" of 5"
A15: How to read it. A channel is credited with new customers by last click. Only some of them would not have bought anyway. If that share is below the break even share, the channel costs more than the twelve month gross profit of the customers it really adds.
A16: Column E is the break even share from the unit economics table: cost per new customer to September 2024 over twelve month gross profit per new customer. Column I is the same at the FY2026 cost the planner uses, three year cost per new customer, with Meta Prospecting raised by the cost per click assumption.
A17: Twelve month gross profit is counted from each new customer's first order, so part of it falls after FY2026. Orders from returning customers that a channel is credited with are left out, which is the cautious direction for brand search and retargeting.
A18: None of these shares has been measured. The only way to measure one is a holdout test; the Recommendation sheet sizes the first.

Sheet Data
A1: Verified figures the planner reads
A2: Every number here is a result from BigQuery project ecomrl. Grey cells are data: do not edit them.
A4: Channel | B4: FY2025 ad spend | C4: FY2025 net revenue, last click | D4: FY2025 gross profit, last click | E4: Gross profit on GA4 journeys, last click | F4: Gross profit on GA4 journeys, position based | G4: ROAS, position based, FY2025 | H4: Cost per new customer, three years | I4: Cost per new customer, to Sep 2024 | J4: 12 month gross profit per new customer | K4: 12 month repeat rate | L4: Share of the journeys it closed that it also opened
A5: Google Brand | B5: 31289.45 | C5: 463062.47 | D5: 289393.07 | E5: 255968.88 | F5: 148994.56 | G5: 8.66 | H5: 15.59 | I5: 14.49 | J5: 131.65 | K5: 0.265 | L5: 0.16
A6: Google Non Brand | B6: 127143.68 | C6: 665377.37 | D6: 414226.03 | E6: 364376.38 | F6: 472747.33 | G6: 6.77 | H6: 34.89 | I6: 33.02 | J6: 134.66 | K6: 0.266 | L6: 0.584
A7: Google Shopping | B7: 80300.48 | C7: 345409.19 | D7: 217829.57 | E7: 192261.12 | F7: 148877.76 | G7: 3.34 | H7: 35.87 | I7: 36.41 | J7: 112.19 | K7: 0.149 | L7: 0.605
A8: Meta Prospecting | B8: 205487.28 | C8: 549909.79 | D8: 359610.65 | E8: 315061.17 | F8: 478299.32 | G8: 4.14 | H8: 52.54 | I8: 53.08 | J8: 92.94 | K8: 0.045 | L8: 0.783
A9: Meta Retargeting | B9: 54727.02 | C9: 336044.12 | D9: 212515.43 | E9: 189059.01 | F9: 97313.52 | G9: 3.15 | H9: 39.85 | I9: 38.84 | J9: 97.26 | K9: 0.069 | L9: 0.122
A10: Total, five channels | B10: =SUM(B5:B9) | C10: =SUM(C5:C9) | D10: =SUM(D5:D9) | E10: =SUM(E5:E9) | F10: =SUM(F5:F9)
A12: Where each column comes from
A13: FY2025 | B13: The financial year 1 October 2024 to 30 September 2025, the year the GA4 export covers.
A14: Columns B to D | B14: clean.channel_daily summed over FY2025, as read by 02_reconciliation_attribution.ipynb, Step 3.3. Net revenue is after discounts and refunds; gross profit is after product, shipping, payment and affiliate costs, before ad spend.
A15: Columns E and F | B15: Gross profit credited to the channel on the 27,905 orders GA4 saw, under last click and under position based (40 percent to the first session, 40 to the last, 20 across the middle). 02_reconciliation_attribution.ipynb, Step 3.3. Their ratio is how much of its credit a channel keeps once earlier sessions share it.
A16: Column G | B16: Net revenue per dollar of spend under position based, FY2025, as printed to two decimals by the same step.
A17: Columns H to J | B17: ecomrl.clean.unit_economics, written by 01_customer_value.ipynb. Cost per new customer is ad spend over the channel's new customers, all spend charged to acquisition. Column I uses spend and new customers to 30 September 2024 so that cost and twelve month value describe the same people.
A18: Columns K and L | B18: Repeat rate from unit_economics (new customers who ordered again within twelve months). Share also opened from 02_reconciliation_attribution.ipynb, Step 3.4.
A20: Other verified figures
A21: Figure | B21: Value | C21: Source
A22: Affiliate commission still standing, three years | B22: 227336.14 | C22: clean.affiliate_transactions
A23: Saved by Pay on credit and Refund hold together, three years | B23: 132606.99 | C23: 02_reconciliation_attribution.ipynb, Step 4.2. Pay on credit: coupon partners paid only on orders credited to them. Refund hold: commission held 45 days and dropped if the order is refunded in that time
A24: Years those figures cover | B24: 3 | C24: 1 October 2022 to 30 September 2025
A25: Meta Prospecting cost per click, Oct to Dec 2022 | B25: 0.631 | C25: 04_reporting_tables.sql, section 5, Meta Prospecting cost by quarter
A26: Meta Prospecting cost per click, Jul to Sep 2025 | B26: 0.784 | C26: 04_reporting_tables.sql, section 5, Meta Prospecting cost by quarter
A27: Years between those two quarters | B27: 2.75 | C27: Eleven quarters
A28: Meta Prospecting clicks that became orders, Jul to Sep 2023 | B28: 0.0136 | C28: 04_reporting_tables.sql, section 5, Meta Prospecting cost by quarter
A29: Meta Prospecting clicks that became orders, Jul to Sep 2025 | B29: 0.0162 | C29: 04_reporting_tables.sql, section 5, Meta Prospecting cost by quarter
A30: Meta Prospecting checkout to purchase, GA4 year | B30: 0.127 | C30: clean.funnel_daily over the GA4 year, all devices (3,472 of 27,364 sessions that reached checkout). By device in 04_reporting_tables.sql, section 6: 14.8 desktop, 11.4 mobile, 13.0 tablet
A31: Google traffic checkout to purchase, GA4 year | B31: 0.38 | C31: clean.funnel_daily, Google family over the GA4 year, as on the report Funnel page
A32: UK net revenue, three years | B32: 2990792 | C32: clean.channel_daily, UK
A33: All net revenue, three years | B33: 11907875 | C33: clean.channel_daily
A34: Meta Prospecting cost per click growth a year, measured | B34: =(B26/B25)^(1/B27)-1 | C34: Calculated from the two quarters above
A35: Meta Prospecting click to order growth a year, measured | B35: =(B29/B28)^(1/2)-1 | C35: Same quarter two years apart
A36: UK share of net revenue | B36: =B32/B33 | C36: Calculated from the two rows above
